LICENSE.rst
README.md
setup.py
fastapi_request_limiter.egg-info/PKG-INFO
fastapi_request_limiter.egg-info/SOURCES.txt
fastapi_request_limiter.egg-info/dependency_links.txt
fastapi_request_limiter.egg-info/top_level.txt
request_limiter_middleware/__init__.py
request_limiter_middleware/main.py
request_limiter_middleware/requests_archive.py
request_limiter_middleware/whitelisted_addresses.py