Metadata-Version: 2.1
Name: fastapi-request-limiter
Version: 1.0
Summary: This middleware provides request limiting functionality for FastAPI applications, allowing you to control and manage the rate of incoming requests based on client IP addresses.
Home-page: https://github.com/Armen-Jean-Andreasian
Author: Armen-Jean Andreasian
Author-email: armen_andreasian@proton.me
License: BSD
Keywords: FastAPI,request-limiter,python
Classifier: Topic :: Software Development :: Libraries :: Python Modules
Classifier: Framework :: FastAPI
Classifier: Development Status :: 4 - Beta
Requires-Python: >=3.8
License-File: LICENSE.rst
